destiny/__init__.py
destiny/api.py
destiny/destiny.py
destiny/enums.py
destiny/errors.py
destiny/manifest.py
destiny_hazel_trinity-0.0.3.dist-info/LICENSE
destiny_hazel_trinity-0.0.3.dist-info/METADATA
destiny_hazel_trinity-0.0.3.dist-info/WHEEL
destiny_hazel_trinity-0.0.3.dist-info/top_level.txt
destiny_hazel_trinity-0.0.3.dist-info/RECORD
